.installed.cfg
.mr.developer.cfg
CHANGES.txt
LICENSE
MANIFEST.in
README.rst
README.txt
bootstrap.py
buildout.cfg
cacert.pem
development.ini
pricing.json
production.ini
settings.py.dist
setup.cfg
setup.py
staging.ini
docs/LICENSE.txt
docs/Makefile
docs/make.bat
docs/build/.buildinfo
docs/build/backends_api.html
docs/build/developer_guide.html
docs/build/error_api.html
docs/build/genindex.html
docs/build/http-routingtable.html
docs/build/images_api.html
docs/build/index.html
docs/build/keys_api.html
docs/build/login_api.html
docs/build/machines_api.html
docs/build/modules.html
docs/build/objects.inv
docs/build/providers_api.html
docs/build/py-modindex.html
docs/build/rest_api.html
docs/build/search.html
docs/build/searchindex.js
docs/build/shell_api.html
docs/build/.doctrees/backends_api.doctree
docs/build/.doctrees/developer_guide.doctree
docs/build/.doctrees/environment.pickle
docs/build/.doctrees/error_api.doctree
docs/build/.doctrees/images_api.doctree
docs/build/.doctrees/index.doctree
docs/build/.doctrees/keys_api.doctree
docs/build/.doctrees/login_api.doctree
docs/build/.doctrees/machines_api.doctree
docs/build/.doctrees/modules.doctree
docs/build/.doctrees/providers_api.doctree
docs/build/.doctrees/rest_api.doctree
docs/build/.doctrees/shell_api.doctree
docs/build/_sources/backends_api.txt
docs/build/_sources/developer_guide.txt
docs/build/_sources/error_api.txt
docs/build/_sources/images_api.txt
docs/build/_sources/index.txt
docs/build/_sources/keys_api.txt
docs/build/_sources/login_api.txt
docs/build/_sources/machines_api.txt
docs/build/_sources/modules.txt
docs/build/_sources/providers_api.txt
docs/build/_sources/rest_api.txt
docs/build/_sources/shell_api.txt
docs/build/_static/ajax-loader.gif
docs/build/_static/basic.css
docs/build/_static/bootstrap-sphinx.css
docs/build/_static/bootstrap-sphinx.js
docs/build/_static/comment-bright.png
docs/build/_static/comment-close.png
docs/build/_static/comment.png
docs/build/_static/doctools.js
src/mist.io.egg-info/PKG-INFO
src/mist.io.egg-info/SOURCES.txt
src/mist.io.egg-info/dependency_links.txt
src/mist.io.egg-info/entry_points.txt
src/mist.io.egg-info/namespace_packages.txt
src/mist.io.egg-info/not-zip-safe
src/mist.io.egg-info/requires.txt
src/mist.io.egg-info/top_level.txt
