Metadata-Version: 1.0
Name: mist.io
Version: 0.9.8
Summary: server management, monitoring & automation across clouds from any web device
Home-page: https://mist.io
Author: mist.io
Author-email: info@mist.io
License: AGPLv3
Keywords: web cloud server management monitoring automation mobile libcloud pyramid amazon aws rackspace openstack linode softlayer digitalocean gce
Platform: UNKNOWN
Classifier: Programming Language :: Python
Classifier: Framework :: Pylons
Classifier: Topic :: Internet :: WWW/HTTP
Classifier: License :: OSI Approved :: GNU Affero General Public License v3
Classifier: Topic :: Internet :: WWW/HTTP :: WSGI :: Application
